{
  "id": "ed96f0e0-0918-4369-a714-551eb7bad88f",
  "prevId": "22c12fc3-8962-4d24-99fa-a654bc5d082b",
  "version": "5",
  "dialect": "pg",
  "tables": {
    "agencies": {
      "name": "agencies",
      "schema": "",
      "columns": {
        "id": {
          "name": "id",
          "type": "uuid",
          "primaryKey": true,
          "notNull": true,
          "default": "gen_random_uuid()"
        },
        "name": {
          "name": "name",
          "type": "varchar(255)",
          "primaryKey": false,
          "notNull": true
        },
        "phone": {
          "name": "phone",
          "type": "varchar(12)",
          "primaryKey": false,
          "notNull": true
        },
        "email": {
          "name": "email",
          "type": "varchar(255)",
          "primaryKey": false,
          "notNull": true
        },
        "state": {
          "name": "state",
          "type": "varchar(255)",
          "primaryKey": false,
          "notNull": true
        },
        "invite_code": {
          "name": "invite_code",
          "type": "varchar(20)",
          "primaryKey": false,
          "notNull": false
        },
        "onboarded_via_invite": {
          "name": "onboarded_via_invite",
          "type": "boolean",
          "primaryKey": false,
          "notNull": true,
          "default": false
        },
        "invite_id": {
          "name": "invite_id",
          "type": "uuid",
          "primaryKey": false,
          "notNull": false
        },
        "created_at": {
          "name": "created_at",
          "type": "timestamp with time zone",
          "primaryKey": false,
          "notNull": true,
          "default": "now()"
        }
      },
      "indexes": {},
      "foreignKeys": {
        "agencies_invite_id_agency_invites_id_fk": {
          "name": "agencies_invite_id_agency_invites_id_fk",
          "tableFrom": "agencies",
          "tableTo": "agency_invites",
          "columnsFrom": [
            "invite_id"
          ],
          "columnsTo": [
            "id"
          ],
          "onDelete": "no action",
          "onUpdate": "no action"
        }
      },
      "compositePrimaryKeys": {},
      "uniqueConstraints": {
        "agencies_invite_code_unique": {
          "name": "agencies_invite_code_unique",
          "nullsNotDistinct": false,
          "columns": [
            "invite_code"
          ]
        }
      }
    },
    "agency_invites": {
      "name": "agency_invites",
      "schema": "",
      "columns": {
        "id": {
          "name": "id",
          "type": "uuid",
          "primaryKey": true,
          "notNull": true,
          "default": "gen_random_uuid()"
        },
        "phone": {
          "name": "phone",
          "type": "varchar(20)",
          "primaryKey": false,
          "notNull": true
        },
        "invite_token": {
          "name": "invite_token",
          "type": "uuid",
          "primaryKey": false,
          "notNull": true,
          "default": "gen_random_uuid()"
        },
        "invited_by": {
          "name": "invited_by",
          "type": "uuid",
          "primaryKey": false,
          "notNull": true
        },
        "status": {
          "name": "status",
          "type": "varchar(20)",
          "primaryKey": false,
          "notNull": true,
          "default": "'pending'"
        },
        "expires_at": {
          "name": "expires_at",
          "type": "timestamp with time zone",
          "primaryKey": false,
          "notNull": true
        },
        "created_at": {
          "name": "created_at",
          "type": "timestamp with time zone",
          "primaryKey": false,
          "notNull": true,
          "default": "now()"
        },
        "accepted_at": {
          "name": "accepted_at",
          "type": "timestamp with time zone",
          "primaryKey": false,
          "notNull": false
        }
      },
      "indexes": {},
      "foreignKeys": {},
      "compositePrimaryKeys": {},
      "uniqueConstraints": {
        "agency_invites_invite_token_unique": {
          "name": "agency_invites_invite_token_unique",
          "nullsNotDistinct": false,
          "columns": [
            "invite_token"
          ]
        }
      }
    },
    "agency_wallets": {
      "name": "agency_wallets",
      "schema": "",
      "columns": {
        "id": {
          "name": "id",
          "type": "uuid",
          "primaryKey": true,
          "notNull": true,
          "default": "gen_random_uuid()"
        },
        "agency_id": {
          "name": "agency_id",
          "type": "uuid",
          "primaryKey": false,
          "notNull": true
        },
        "trips_remaining": {
          "name": "trips_remaining",
          "type": "integer",
          "primaryKey": false,
          "notNull": true,
          "default": 0
        },
        "trips_used_this_month": {
          "name": "trips_used_this_month",
          "type": "integer",
          "primaryKey": false,
          "notNull": true,
          "default": 0
        },
        "low_trip_threshold": {
          "name": "low_trip_threshold",
          "type": "integer",
          "primaryKey": false,
          "notNull": true,
          "default": 10
        },
        "created_at": {
          "name": "created_at",
          "type": "timestamp with time zone",
          "primaryKey": false,
          "notNull": true,
          "default": "now()"
        },
        "updated_at": {
          "name": "updated_at",
          "type": "timestamp with time zone",
          "primaryKey": false,
          "notNull": true,
          "default": "now()"
        }
      },
      "indexes": {},
      "foreignKeys": {
        "agency_wallets_agency_id_agencies_id_fk": {
          "name": "agency_wallets_agency_id_agencies_id_fk",
          "tableFrom": "agency_wallets",
          "tableTo": "agencies",
          "columnsFrom": [
            "agency_id"
          ],
          "columnsTo": [
            "id"
          ],
          "onDelete": "no action",
          "onUpdate": "no action"
        }
      },
      "compositePrimaryKeys": {},
      "uniqueConstraints": {
        "agency_wallets_agency_id_unique": {
          "name": "agency_wallets_agency_id_unique",
          "nullsNotDistinct": false,
          "columns": [
            "agency_id"
          ]
        }
      }
    },
    "alert_logs": {
      "name": "alert_logs",
      "schema": "",
      "columns": {
        "id": {
          "name": "id",
          "type": "uuid",
          "primaryKey": true,
          "notNull": true,
          "default": "gen_random_uuid()"
        },
        "trip_passenger_id": {
          "name": "trip_passenger_id",
          "type": "uuid",
          "primaryKey": false,
          "notNull": true
        },
        "channel": {
          "name": "channel",
          "type": "alert_channel",
          "primaryKey": false,
          "notNull": true
        },
        "status": {
          "name": "status",
          "type": "alert_log_status",
          "primaryKey": false,
          "notNull": true
        },
        "attempted_at": {
          "name": "attempted_at",
          "type": "timestamp with time zone",
          "primaryKey": false,
          "notNull": true,
          "default": "now()"
        },
        "response_code": {
          "name": "response_code",
          "type": "varchar(64)",
          "primaryKey": false,
          "notNull": false
        },
        "error_message": {
          "name": "error_message",
          "type": "text",
          "primaryKey": false,
          "notNull": false
        }
      },
      "indexes": {
        "alert_logs_passenger_idx": {
          "name": "alert_logs_passenger_idx",
          "columns": [
            "trip_passenger_id"
          ],
          "isUnique": false
        }
      },
      "foreignKeys": {
        "alert_logs_trip_passenger_id_trip_passengers_id_fk": {
          "name": "alert_logs_trip_passenger_id_trip_passengers_id_fk",
          "tableFrom": "alert_logs",
          "tableTo": "trip_passengers",
          "columnsFrom": [
            "trip_passenger_id"
          ],
          "columnsTo": [
            "id"
          ],
          "onDelete": "no action",
          "onUpdate": "no action"
        }
      },
      "compositePrimaryKeys": {},
      "uniqueConstraints": {}
    },
    "audit_logs": {
      "name": "audit_logs",
      "schema": "",
      "columns": {
        "id": {
          "name": "id",
          "type": "uuid",
          "primaryKey": true,
          "notNull": true,
          "default": "gen_random_uuid()"
        },
        "user_id": {
          "name": "user_id",
          "type": "uuid",
          "primaryKey": false,
          "notNull": false
        },
        "action": {
          "name": "action",
          "type": "varchar(255)",
          "primaryKey": false,
          "notNull": true
        },
        "entity_type": {
          "name": "entity_type",
          "type": "varchar(255)",
          "primaryKey": false,
          "notNull": true
        },
        "entity_id": {
          "name": "entity_id",
          "type": "varchar(255)",
          "primaryKey": false,
          "notNull": false
        },
        "metadata": {
          "name": "metadata",
          "type": "jsonb",
          "primaryKey": false,
          "notNull": false
        },
        "ip_address": {
          "name": "ip_address",
          "type": "varchar(64)",
          "primaryKey": false,
          "notNull": false
        },
        "created_at": {
          "name": "created_at",
          "type": "timestamp with time zone",
          "primaryKey": false,
          "notNull": true,
          "default": "now()"
        }
      },
      "indexes": {},
      "foreignKeys": {
        "audit_logs_user_id_users_id_fk": {
          "name": "audit_logs_user_id_users_id_fk",
          "tableFrom": "audit_logs",
          "tableTo": "users",
          "columnsFrom": [
            "user_id"
          ],
          "columnsTo": [
            "id"
          ],
          "onDelete": "no action",
          "onUpdate": "no action"
        }
      },
      "compositePrimaryKeys": {},
      "uniqueConstraints": {}
    },
    "conductor_locations": {
      "name": "conductor_locations",
      "schema": "",
      "columns": {
        "id": {
          "name": "id",
          "type": "uuid",
          "primaryKey": true,
          "notNull": true,
          "default": "gen_random_uuid()"
        },
        "trip_id": {
          "name": "trip_id",
          "type": "uuid",
          "primaryKey": false,
          "notNull": true
        },
        "conductor_id": {
          "name": "conductor_id",
          "type": "uuid",
          "primaryKey": false,
          "notNull": true
        },
        "coordinates": {
          "name": "coordinates",
          "type": "geometry(Point, 4326)",
          "primaryKey": false,
          "notNull": true
        },
        "recorded_at": {
          "name": "recorded_at",
          "type": "timestamp with time zone",
          "primaryKey": false,
          "notNull": true,
          "default": "now()"
        },
        "battery_level": {
          "name": "battery_level",
          "type": "numeric(5, 2)",
          "primaryKey": false,
          "notNull": false
        },
        "accuracy_meters": {
          "name": "accuracy_meters",
          "type": "numeric(8, 2)",
          "primaryKey": false,
          "notNull": false
        }
      },
      "indexes": {
        "conductor_loc_trip_time_idx": {
          "name": "conductor_loc_trip_time_idx",
          "columns": [
            "trip_id",
            "recorded_at"
          ],
          "isUnique": false
        }
      },
      "foreignKeys": {
        "conductor_locations_trip_id_trips_id_fk": {
          "name": "conductor_locations_trip_id_trips_id_fk",
          "tableFrom": "conductor_locations",
          "tableTo": "trips",
          "columnsFrom": [
            "trip_id"
          ],
          "columnsTo": [
            "id"
          ],
          "onDelete": "no action",
          "onUpdate": "no action"
        },
        "conductor_locations_conductor_id_users_id_fk": {
          "name": "conductor_locations_conductor_id_users_id_fk",
          "tableFrom": "conductor_locations",
          "tableTo": "users",
          "columnsFrom": [
            "conductor_id"
          ],
          "columnsTo": [
            "id"
          ],
          "onDelete": "no action",
          "onUpdate": "no action"
        }
      },
      "compositePrimaryKeys": {},
      "uniqueConstraints": {}
    },
    "refresh_tokens": {
      "name": "refresh_tokens",
      "schema": "",
      "columns": {
        "id": {
          "name": "id",
          "type": "uuid",
          "primaryKey": true,
          "notNull": true,
          "default": "gen_random_uuid()"
        },
        "user_id": {
          "name": "user_id",
          "type": "uuid",
          "primaryKey": false,
          "notNull": true
        },
        "token_hash": {
          "name": "token_hash",
          "type": "text",
          "primaryKey": false,
          "notNull": true
        },
        "expires_at": {
          "name": "expires_at",
          "type": "timestamp with time zone",
          "primaryKey": false,
          "notNull": true
        },
        "created_at": {
          "name": "created_at",
          "type": "timestamp with time zone",
          "primaryKey": false,
          "notNull": true,
          "default": "now()"
        }
      },
      "indexes": {},
      "foreignKeys": {
        "refresh_tokens_user_id_users_id_fk": {
          "name": "refresh_tokens_user_id_users_id_fk",
          "tableFrom": "refresh_tokens",
          "tableTo": "users",
          "columnsFrom": [
            "user_id"
          ],
          "columnsTo": [
            "id"
          ],
          "onDelete": "no action",
          "onUpdate": "no action"
        }
      },
      "compositePrimaryKeys": {},
      "uniqueConstraints": {}
    },
    "routes": {
      "name": "routes",
      "schema": "",
      "columns": {
        "id": {
          "name": "id",
          "type": "uuid",
          "primaryKey": true,
          "notNull": true,
          "default": "gen_random_uuid()"
        },
        "agency_id": {
          "name": "agency_id",
          "type": "uuid",
          "primaryKey": false,
          "notNull": true
        },
        "name": {
          "name": "name",
          "type": "varchar(255)",
          "primaryKey": false,
          "notNull": true
        },
        "from_city": {
          "name": "from_city",
          "type": "varchar(255)",
          "primaryKey": false,
          "notNull": true
        },
        "to_city": {
          "name": "to_city",
          "type": "varchar(255)",
          "primaryKey": false,
          "notNull": true
        },
        "created_at": {
          "name": "created_at",
          "type": "timestamp with time zone",
          "primaryKey": false,
          "notNull": true,
          "default": "now()"
        }
      },
      "indexes": {
        "routes_agency_idx": {
          "name": "routes_agency_idx",
          "columns": [
            "agency_id"
          ],
          "isUnique": false
        }
      },
      "foreignKeys": {
        "routes_agency_id_agencies_id_fk": {
          "name": "routes_agency_id_agencies_id_fk",
          "tableFrom": "routes",
          "tableTo": "agencies",
          "columnsFrom": [
            "agency_id"
          ],
          "columnsTo": [
            "id"
          ],
          "onDelete": "no action",
          "onUpdate": "no action"
        }
      },
      "compositePrimaryKeys": {},
      "uniqueConstraints": {}
    },
    "stops": {
      "name": "stops",
      "schema": "",
      "columns": {
        "id": {
          "name": "id",
          "type": "uuid",
          "primaryKey": true,
          "notNull": true,
          "default": "gen_random_uuid()"
        },
        "route_id": {
          "name": "route_id",
          "type": "uuid",
          "primaryKey": false,
          "notNull": true
        },
        "name": {
          "name": "name",
          "type": "varchar(255)",
          "primaryKey": false,
          "notNull": true
        },
        "sequence_number": {
          "name": "sequence_number",
          "type": "integer",
          "primaryKey": false,
          "notNull": true
        },
        "coordinates": {
          "name": "coordinates",
          "type": "geometry(Point, 4326)",
          "primaryKey": false,
          "notNull": true
        },
        "trigger_radius_km": {
          "name": "trigger_radius_km",
          "type": "numeric(5, 2)",
          "primaryKey": false,
          "notNull": true,
          "default": "'10'"
        }
      },
      "indexes": {},
      "foreignKeys": {
        "stops_route_id_routes_id_fk": {
          "name": "stops_route_id_routes_id_fk",
          "tableFrom": "stops",
          "tableTo": "routes",
          "columnsFrom": [
            "route_id"
          ],
          "columnsTo": [
            "id"
          ],
          "onDelete": "no action",
          "onUpdate": "no action"
        }
      },
      "compositePrimaryKeys": {},
      "uniqueConstraints": {}
    },
    "trip_passengers": {
      "name": "trip_passengers",
      "schema": "",
      "columns": {
        "id": {
          "name": "id",
          "type": "uuid",
          "primaryKey": true,
          "notNull": true,
          "default": "gen_random_uuid()"
        },
        "trip_id": {
          "name": "trip_id",
          "type": "uuid",
          "primaryKey": false,
          "notNull": true
        },
        "passenger_name": {
          "name": "passenger_name",
          "type": "varchar(255)",
          "primaryKey": false,
          "notNull": true
        },
        "passenger_phone": {
          "name": "passenger_phone",
          "type": "varchar(20)",
          "primaryKey": false,
          "notNull": true
        },
        "stop_id": {
          "name": "stop_id",
          "type": "uuid",
          "primaryKey": false,
          "notNull": true
        },
        "alert_status": {
          "name": "alert_status",
          "type": "alert_status",
          "primaryKey": false,
          "notNull": true,
          "default": "'pending'"
        },
        "alert_channel": {
          "name": "alert_channel",
          "type": "alert_channel",
          "primaryKey": false,
          "notNull": false
        },
        "alert_sent_at": {
          "name": "alert_sent_at",
          "type": "timestamp with time zone",
          "primaryKey": false,
          "notNull": false
        },
        "created_at": {
          "name": "created_at",
          "type": "timestamp with time zone",
          "primaryKey": false,
          "notNull": true,
          "default": "now()"
        }
      },
      "indexes": {
        "trip_passengers_trip_status_idx": {
          "name": "trip_passengers_trip_status_idx",
          "columns": [
            "trip_id",
            "alert_status"
          ],
          "isUnique": false
        }
      },
      "foreignKeys": {
        "trip_passengers_trip_id_trips_id_fk": {
          "name": "trip_passengers_trip_id_trips_id_fk",
          "tableFrom": "trip_passengers",
          "tableTo": "trips",
          "columnsFrom": [
            "trip_id"
          ],
          "columnsTo": [
            "id"
          ],
          "onDelete": "no action",
          "onUpdate": "no action"
        },
        "trip_passengers_stop_id_stops_id_fk": {
          "name": "trip_passengers_stop_id_stops_id_fk",
          "tableFrom": "trip_passengers",
          "tableTo": "stops",
          "columnsFrom": [
            "stop_id"
          ],
          "columnsTo": [
            "id"
          ],
          "onDelete": "no action",
          "onUpdate": "no action"
        }
      },
      "compositePrimaryKeys": {},
      "uniqueConstraints": {}
    },
    "trips": {
      "name": "trips",
      "schema": "",
      "columns": {
        "id": {
          "name": "id",
          "type": "uuid",
          "primaryKey": true,
          "notNull": true,
          "default": "gen_random_uuid()"
        },
        "route_id": {
          "name": "route_id",
          "type": "uuid",
          "primaryKey": false,
          "notNull": true
        },
        "operator_id": {
          "name": "operator_id",
          "type": "uuid",
          "primaryKey": false,
          "notNull": true
        },
        "conductor_id": {
          "name": "conductor_id",
          "type": "uuid",
          "primaryKey": false,
          "notNull": true
        },
        "driver_id": {
          "name": "driver_id",
          "type": "uuid",
          "primaryKey": false,
          "notNull": false
        },
        "status": {
          "name": "status",
          "type": "trip_status",
          "primaryKey": false,
          "notNull": true,
          "default": "'scheduled'"
        },
        "scheduled_date": {
          "name": "scheduled_date",
          "type": "date",
          "primaryKey": false,
          "notNull": true
        },
        "started_at": {
          "name": "started_at",
          "type": "timestamp with time zone",
          "primaryKey": false,
          "notNull": false
        },
        "completed_at": {
          "name": "completed_at",
          "type": "timestamp with time zone",
          "primaryKey": false,
          "notNull": false
        },
        "created_at": {
          "name": "created_at",
          "type": "timestamp with time zone",
          "primaryKey": false,
          "notNull": true,
          "default": "now()"
        }
      },
      "indexes": {},
      "foreignKeys": {
        "trips_route_id_routes_id_fk": {
          "name": "trips_route_id_routes_id_fk",
          "tableFrom": "trips",
          "tableTo": "routes",
          "columnsFrom": [
            "route_id"
          ],
          "columnsTo": [
            "id"
          ],
          "onDelete": "no action",
          "onUpdate": "no action"
        },
        "trips_operator_id_users_id_fk": {
          "name": "trips_operator_id_users_id_fk",
          "tableFrom": "trips",
          "tableTo": "users",
          "columnsFrom": [
            "operator_id"
          ],
          "columnsTo": [
            "id"
          ],
          "onDelete": "no action",
          "onUpdate": "no action"
        },
        "trips_conductor_id_users_id_fk": {
          "name": "trips_conductor_id_users_id_fk",
          "tableFrom": "trips",
          "tableTo": "users",
          "columnsFrom": [
            "conductor_id"
          ],
          "columnsTo": [
            "id"
          ],
          "onDelete": "no action",
          "onUpdate": "no action"
        },
        "trips_driver_id_users_id_fk": {
          "name": "trips_driver_id_users_id_fk",
          "tableFrom": "trips",
          "tableTo": "users",
          "columnsFrom": [
            "driver_id"
          ],
          "columnsTo": [
            "id"
          ],
          "onDelete": "no action",
          "onUpdate": "no action"
        }
      },
      "compositePrimaryKeys": {},
      "uniqueConstraints": {}
    },
    "users": {
      "name": "users",
      "schema": "",
      "columns": {
        "id": {
          "name": "id",
          "type": "uuid",
          "primaryKey": true,
          "notNull": true,
          "default": "gen_random_uuid()"
        },
        "agency_id": {
          "name": "agency_id",
          "type": "uuid",
          "primaryKey": false,
          "notNull": false
        },
        "name": {
          "name": "name",
          "type": "varchar(255)",
          "primaryKey": false,
          "notNull": true
        },
        "phone": {
          "name": "phone",
          "type": "varchar(20)",
          "primaryKey": false,
          "notNull": false
        },
        "email": {
          "name": "email",
          "type": "varchar(255)",
          "primaryKey": false,
          "notNull": false
        },
        "password_hash": {
          "name": "password_hash",
          "type": "text",
          "primaryKey": false,
          "notNull": true
        },
        "role": {
          "name": "role",
          "type": "role",
          "primaryKey": false,
          "notNull": true
        },
        "is_active": {
          "name": "is_active",
          "type": "boolean",
          "primaryKey": false,
          "notNull": true,
          "default": true
        },
        "created_at": {
          "name": "created_at",
          "type": "timestamp with time zone",
          "primaryKey": false,
          "notNull": true,
          "default": "now()"
        }
      },
      "indexes": {},
      "foreignKeys": {
        "users_agency_id_agencies_id_fk": {
          "name": "users_agency_id_agencies_id_fk",
          "tableFrom": "users",
          "tableTo": "agencies",
          "columnsFrom": [
            "agency_id"
          ],
          "columnsTo": [
            "id"
          ],
          "onDelete": "no action",
          "onUpdate": "no action"
        }
      },
      "compositePrimaryKeys": {},
      "uniqueConstraints": {
        "users_phone_unique": {
          "name": "users_phone_unique",
          "nullsNotDistinct": false,
          "columns": [
            "phone"
          ]
        }
      }
    },
    "wallet_transactions": {
      "name": "wallet_transactions",
      "schema": "",
      "columns": {
        "id": {
          "name": "id",
          "type": "uuid",
          "primaryKey": true,
          "notNull": true,
          "default": "gen_random_uuid()"
        },
        "agency_id": {
          "name": "agency_id",
          "type": "uuid",
          "primaryKey": false,
          "notNull": true
        },
        "trips_amount": {
          "name": "trips_amount",
          "type": "integer",
          "primaryKey": false,
          "notNull": true
        },
        "trips_remaining_after": {
          "name": "trips_remaining_after",
          "type": "integer",
          "primaryKey": false,
          "notNull": true
        },
        "type": {
          "name": "type",
          "type": "wallet_tx_type",
          "primaryKey": false,
          "notNull": true
        },
        "description": {
          "name": "description",
          "type": "text",
          "primaryKey": false,
          "notNull": false
        },
        "reference_id": {
          "name": "reference_id",
          "type": "varchar(255)",
          "primaryKey": false,
          "notNull": false
        },
        "created_at": {
          "name": "created_at",
          "type": "timestamp with time zone",
          "primaryKey": false,
          "notNull": true,
          "default": "now()"
        }
      },
      "indexes": {
        "wallet_tx_agency_idx": {
          "name": "wallet_tx_agency_idx",
          "columns": [
            "agency_id",
            "created_at"
          ],
          "isUnique": false
        }
      },
      "foreignKeys": {
        "wallet_transactions_agency_id_agencies_id_fk": {
          "name": "wallet_transactions_agency_id_agencies_id_fk",
          "tableFrom": "wallet_transactions",
          "tableTo": "agencies",
          "columnsFrom": [
            "agency_id"
          ],
          "columnsTo": [
            "id"
          ],
          "onDelete": "no action",
          "onUpdate": "no action"
        }
      },
      "compositePrimaryKeys": {},
      "uniqueConstraints": {}
    }
  },
  "enums": {
    "alert_channel": {
      "name": "alert_channel",
      "values": {
        "call": "call",
        "sms": "sms",
        "whatsapp": "whatsapp",
        "manual": "manual"
      }
    },
    "alert_log_status": {
      "name": "alert_log_status",
      "values": {
        "success": "success",
        "failed": "failed"
      }
    },
    "alert_status": {
      "name": "alert_status",
      "values": {
        "pending": "pending",
        "sent": "sent",
        "failed": "failed"
      }
    },
    "trip_status": {
      "name": "trip_status",
      "values": {
        "scheduled": "scheduled",
        "active": "active",
        "completed": "completed"
      }
    },
    "role": {
      "name": "role",
      "values": {
        "admin": "admin",
        "owner": "owner",
        "operator": "operator",
        "driver": "driver",
        "conductor": "conductor",
        "passenger": "passenger"
      }
    },
    "wallet_tx_type": {
      "name": "wallet_tx_type",
      "values": {
        "trip_topup": "trip_topup",
        "trip_deduction": "trip_deduction"
      }
    }
  },
  "schemas": {},
  "_meta": {
    "columns": {},
    "schemas": {},
    "tables": {}
  }
}